/* ******************************************** */
/* Generated by Dr. Garbage Bytecode Visualizer */
/* http://www.drgarbage.com                     */
/* Version: 4.4.1.201408050542                  */
/* Class retrieved from: Filesystem             */
/* Retrieved on: 2014-09-22 17:27:53.999        */
/* ******************************************** */

/* class file format version 52.0 (java 1.8) */
package byteCodeCompare;

public class ExampleByteCode2 {

    /* compiled from ExampleByteCode2.java */

    public ExampleByteCode2() {
        /* L5 */
        0 aload_0;                /* this */
        1 invokespecial 8;        /* java.lang.Object() */
        4 return;
    }

    public void main(java.lang.String[] k) {
        /* L9 */
        0 iconst_0;
        1 istore_2;               /* k */
        /* L10 */
        2 aload_0;                /* this */
        3 invokevirtual 16;       /* int getnumber() */
        6 istore_2;               /* k */
        /* L11 */
        7 iload_2;                /* k */
        8 iconst_5;
        9 if_icmple 14;
        /* L12 */
        12 getstatic 20;          /* java.lang.System.out */
        15 ldc 26;                /* "i > 5" */
        17 invokevirtual 28;      /* void println(java.lang.String k) */
        /* L13 */
        20 goto 11;
        /* L15 */
        23 getstatic 20;          /* java.lang.System.out */
        26 ldc 34;                /* "i < 5" */
        28 invokevirtual 28;      /* void println(java.lang.String k) */
        /* L17 */
        31 return;
    }

    public int getnumber() {
        /* L20 */
        0 new 41;
        3 dup;
        4 invokespecial 43;       /* java.util.Random() */
        7 astore_1;               /* randomV */
        /* L21 */
        8 aload_1;                /* randomV */
        9 bipush 10;
        11 invokevirtual 44;      /* int nextInt(int arg0) */
        14 ireturn;
    }
}
